S15lib/__init__.py
S15lib/apps/DPG_Mermaid_parser.py
S15lib/apps/__init__.py
S15lib/apps/align_source.py
S15lib/apps/inst_efficiency.py
S15lib/apps/powermeter_app.py
S15lib/g2lib/__init__.py
S15lib/g2lib/coinc4.pyx
S15lib/g2lib/delta.c
S15lib/g2lib/delta.cpython-313-x86_64-linux-gnu.so
S15lib/g2lib/delta.cpython-313-x86_64-linux-musl.so
S15lib/g2lib/delta.pyx
S15lib/g2lib/g2lib.py
S15lib/g2lib/parse_timestamps.py
S15lib/instruments/__init__.py
S15lib/instruments/digital_pattern_generator.py
S15lib/instruments/lcr_driver.py
S15lib/instruments/powermeter.py
S15lib/instruments/serial_connection.py
S15lib/instruments/single_photon_detector.py
S15lib/instruments/spdc_driver.py
S15lib/instruments/stepper_motor_driver.py
S15lib/instruments/timestamp7.py
S15lib/instruments/universal_discriminator.py
S15lib/instruments/usb_counter_fpga.py
s15lib-0.3.0.dist-info/METADATA
s15lib-0.3.0.dist-info/WHEEL
s15lib-0.3.0.dist-info/top_level.txt
s15lib-0.3.0.dist-info/RECORD
s15lib-0.3.0.dist-info/licenses/LICENSE
