Metadata-Version: 2.4
Name: S15lib
Version: 0.3.0
Summary: S-Fifteen Python Library
Author: Mathias Seidler
Maintainer-email: S-Fifteen Instruments <info@s-fifteen.com>, Justin Peh <pehyuxiang@gmail.com>
License: MIT
Keywords: instrumentation
Classifier: Development Status :: 4 - Beta
Classifier: Intended Audience :: Developers
Classifier: Intended Audience :: Science/Research
Classifier: License :: OSI Approved :: MIT License
Classifier: Natural Language :: English
Classifier: Operating System :: OS Independent
Classifier: Programming Language :: Python :: 3
Classifier: Topic :: Scientific/Engineering :: Physics
Requires-Python: >=3.7
License-File: LICENSE
Requires-Dist: psutil
Requires-Dist: pyserial
Requires-Dist: numpy
Requires-Dist: fpfind; python_version >= "3.8"
Provides-Extra: dev
Requires-Dist: pre-commit; extra == "dev"
Requires-Dist: Cython; extra == "dev"
Provides-Extra: apps
Requires-Dist: PyQt5; extra == "apps"
Requires-Dist: Pyqtgraph; extra == "apps"
Requires-Dist: configargparse; extra == "apps"
Dynamic: license
Dynamic: license-file
